hwtSimApi/__init__.py
hwtSimApi/constants.py
hwtSimApi/hdlSimulator.py
hwtSimApi/process_utils.py
hwtSimApi/simCalendar.py
hwtSimApi/triggers.py
hwtSimApi/utils.py
hwtSimApi/agents/__init__.py
hwtSimApi/agents/base.py
hwtSimApi/agents/clk.py
hwtSimApi/agents/handshaked.py
hwtSimApi/agents/rst.py
hwtSimApi/agents/peripheral/__init__.py
hwtSimApi/agents/peripheral/i2c.py
hwtSimApi/agents/peripheral/tristate.py
hwtSimApi/agents/peripheral/uart.py
hwtSimApi/basic_hdl_simulator/__init__.py
hwtSimApi/basic_hdl_simulator/io.py
hwtSimApi/basic_hdl_simulator/model.py
hwtSimApi/basic_hdl_simulator/model_utils.py
hwtSimApi/basic_hdl_simulator/proxy.py
hwtSimApi/basic_hdl_simulator/rtlSimulator.py
hwtSimApi/basic_hdl_simulator/sim_utils.py
hwtSimApi-1.3.dist-info/METADATA
hwtSimApi-1.3.dist-info/WHEEL
hwtSimApi-1.3.dist-info/top_level.txt
hwtSimApi-1.3.dist-info/zip-safe
hwtSimApi-1.3.dist-info/RECORD
